hvac_ikame/__init__.py
hvac_ikame/adapters.py
hvac_ikame/api/__init__.py
hvac_ikame/api/auth_methods/__init__.py
hvac_ikame/api/auth_methods/approle.py
hvac_ikame/api/auth_methods/aws.py
hvac_ikame/api/auth_methods/azure.py
hvac_ikame/api/auth_methods/cert.py
hvac_ikame/api/auth_methods/gcp.py
hvac_ikame/api/auth_methods/github.py
hvac_ikame/api/auth_methods/jwt.py
hvac_ikame/api/auth_methods/kubernetes.py
hvac_ikame/api/auth_methods/ldap.py
hvac_ikame/api/auth_methods/legacy_mfa.py
hvac_ikame/api/auth_methods/oidc.py
hvac_ikame/api/auth_methods/okta.py
hvac_ikame/api/auth_methods/radius.py
hvac_ikame/api/auth_methods/token.py
hvac_ikame/api/auth_methods/userpass.py
hvac_ikame/api/secrets_engines/__init__.py
hvac_ikame/api/secrets_engines/active_directory.py
hvac_ikame/api/secrets_engines/aws.py
hvac_ikame/api/secrets_engines/azure.py
hvac_ikame/api/secrets_engines/consul.py
hvac_ikame/api/secrets_engines/database.py
hvac_ikame/api/secrets_engines/gcp.py
hvac_ikame/api/secrets_engines/identity.py
hvac_ikame/api/secrets_engines/kv.py
hvac_ikame/api/secrets_engines/kv_v1.py
hvac_ikame/api/secrets_engines/kv_v2.py
hvac_ikame/api/secrets_engines/ldap.py
hvac_ikame/api/secrets_engines/pki.py
hvac_ikame/api/secrets_engines/rabbitmq.py
hvac_ikame/api/secrets_engines/ssh.py
hvac_ikame/api/secrets_engines/transform.py
hvac_ikame/api/secrets_engines/transit.py
hvac_ikame/api/system_backend/__init__.py
hvac_ikame/api/system_backend/audit.py
hvac_ikame/api/system_backend/auth.py
hvac_ikame/api/system_backend/capabilities.py
hvac_ikame/api/system_backend/health.py
hvac_ikame/api/system_backend/init.py
hvac_ikame/api/system_backend/key.py
hvac_ikame/api/system_backend/leader.py
hvac_ikame/api/system_backend/lease.py
hvac_ikame/api/system_backend/mount.py
hvac_ikame/api/system_backend/namespace.py
hvac_ikame/api/system_backend/policies.py
hvac_ikame/api/system_backend/policy.py
hvac_ikame/api/system_backend/quota.py
hvac_ikame/api/system_backend/raft.py
hvac_ikame-0.0.1.dist-info/LICENSE.txt
hvac_ikame-0.0.1.dist-info/METADATA
hvac_ikame-0.0.1.dist-info/WHEEL
hvac_ikame-0.0.1.dist-info/RECORD
